{
  "publicPath": "/public/",
  "all": [
    "0.31d7bbb85944f245fb8c.js",
    "1.4dbd89afdbcdf1a61788.js",
    "2.3addf3d2c7eda3b80131.js",
    "vendor.9f326eb78b04d9d51d46.js",
    "app.47d8adc9c4bc5d44e7d4.js",
    "manifest.9e5bc538f921f126d152.js",
    "common.47d8adc9c4bc5d44e7d4.css"
  ],
  "initial": [
    "manifest.9e5bc538f921f126d152.js",
    "vendor.9f326eb78b04d9d51d46.js",
    "app.47d8adc9c4bc5d44e7d4.js"
  ],
  "async": [
    "0.31d7bbb85944f245fb8c.js",
    "1.4dbd89afdbcdf1a61788.js",
    "2.3addf3d2c7eda3b80131.js"
  ],
  "modules": {
    "77639267": [
      3
    ],
    "1e795d95": [
      3
    ],
    "84049a12": [
      3
    ],
    "32cd174e": [
      3
    ],
    "312906f7": [
      3
    ],
    "37d38054": [
      3
    ],
    "06af436e": [
      3
    ],
    "d94279dc": [
      3
    ],
    "208707e4": [
      3
    ],
    "572dafb4": [
      3
    ],
    "581e175e": [
      3
    ],
    "201e9554": [
      3
    ],
    "c7e18888": [
      3
    ],
    "c7444022": [
      3
    ],
    "b84fd2c8": [
      3
    ],
    "2657b01c": [
      3
    ],
    "b187ed66": [
      3
    ],
    "55274b5e": [
      3
    ],
    "30c6e281": [
      3
    ],
    "7c83254a": [
      3
    ],
    "2fa08861": [
      3
    ],
    "1bb92ad1": [
      3
    ],
    "6e72f341": [
      3
    ],
    "046d5fa8": [
      3
    ],
    "4932c842": [
      3
    ],
    "e8a26812": [
      3
    ],
    "ead125a4": [
      3
    ],
    "58ffbf72": [
      3
    ],
    "2096cd1d": [
      3
    ],
    "1144de66": [
      3
    ],
    "212ee066": [
      3
    ],
    "52d66d74": [
      3
    ],
    "5cf8e0f5": [
      3
    ],
    "44e14b7c": [
      3
    ],
    "86b4c6e6": [
      3
    ],
    "add634da": [
      3
    ],
    "7c69c3ed": [
      3
    ],
    "52105cb3": [
      3
    ],
    "aa001a84": [
      3
    ],
    "583cffc5": [
      3
    ],
    "8b1dfdb4": [
      3
    ],
    "390727d8": [
      4,
      6
    ],
    "5f429026": [
      3
    ],
    "13c5759d": [
      3
    ],
    "3e3ac093": [
      4,
      6
    ],
    "a2cdd20e": [
      4,
      6
    ],
    "b9d638d8": [
      4,
      6
    ],
    "668aa186": [
      4,
      6
    ],
    "0bbb0fbb": [
      4,
      6
    ],
    "7fecc752": [
      3
    ],
    "f5e0a822": [
      3
    ],
    "434c5385": [
      3
    ],
    "0c67c14f": [
      3
    ],
    "5c8fe221": [
      3
    ],
    "548b44f9": [
      3
    ],
    "06dcdcdd": [
      3
    ],
    "e56ef97e": [
      3
    ],
    "c06e1ec0": [
      3
    ],
    "856ed3e4": [
      3
    ],
    "1a93fbc7": [
      3
    ],
    "1eae5363": [
      3
    ],
    "ddbd74f6": [
      3
    ],
    "0342eb04": [
      3
    ],
    "e5c56f96": [
      3
    ],
    "3ac8094d": [
      3
    ],
    "5e60052c": [
      3
    ],
    "b68661c2": [
      3
    ],
    "ac4cf100": [
      3
    ],
    "e619ce20": [
      3
    ],
    "84fe7a78": [
      3
    ],
    "43d111d4": [
      3
    ],
    "0600312c": [
      3
    ],
    "6c0edc05": [
      3
    ],
    "08f21be8": [
      3
    ],
    "3af77723": [
      3
    ],
    "3f7afe35": [
      3
    ],
    "1d24263d": [
      3
    ],
    "328f8fee": [
      3
    ],
    "703804da": [
      3
    ],
    "63070f06": [
      3
    ],
    "484e79fc": [
      3
    ],
    "66e0ee72": [
      3
    ],
    "f59dbea8": [
      3
    ],
    "42b12d18": [
      3
    ],
    "1e44d35f": [
      3
    ],
    "3d28b9d8": [
      4,
      6
    ],
    "1d6f55cb": [
      3
    ],
    "82abdc68": [
      3
    ],
    "68e82f4a": [
      4,
      6
    ],
    "7fd93bfe": [
      3
    ],
    "d6a65780": [
      3
    ],
    "b3e5c2a0": [
      3
    ],
    "7705c94e": [
      4,
      6
    ],
    "4164dc4e": [
      4,
      6
    ],
    "01d68441": [
      4,
      6
    ],
    "539e771d": [
      4,
      6
    ],
    "16afc247": [
      3
    ],
    "bddfc7ce": [
      4,
      6
    ],
    "07e335e1": [
      3
    ],
    "010083e4": [
      3
    ],
    "3652a1cc": [
      3
    ],
    "70cdf910": [
      3
    ],
    "15031cc3": [
      3
    ],
    "19a550a7": [
      4,
      6
    ],
    "1910f62a": [
      4,
      6
    ],
    "db1cb704": [
      0
    ],
    "1b79eec6": [
      2
    ],
    "39ffe164": [
      1
    ],
    "2fb66dba": [
      0
    ],
    "2622f3c8": [
      0
    ],
    "5a43b642": [
      2
    ],
    "c0af96f6": [
      0
    ],
    "2e28ee88": [
      1
    ]
  }
}